pyxcpcalibapi-0.0.2.dist-info/licenses/LICENSE
xcp_calib_api/__init__.py
xcp_calib_api/xcp_cal_service.py
pyxcpcalibapi-0.0.2.dist-info/METADATA
pyxcpcalibapi-0.0.2.dist-info/WHEEL
pyxcpcalibapi-0.0.2.dist-info/top_level.txt
pyxcpcalibapi-0.0.2.dist-info/RECORD
