Metadata-Version: 2.4
Name: PyXcpcalibApi
Version: 0.0.2
Summary: High lelve API to access calibration and measurement.
Home-page: https://github.com/sgnes/XCP-Calibration-Api
Author: Sgnes
Author-email: sgnes0514@gmai.com
Classifier: Programming Language :: Python :: 3
Classifier: License :: OSI Approved :: MIT License
Classifier: Operating System :: OS Independent
Requires-Python: >=3.8
License-File: LICENSE
Requires-Dist: pya2lparser
Requires-Dist: pyxcpcanmaster
Dynamic: author
Dynamic: author-email
Dynamic: classifier
Dynamic: description
Dynamic: description-content-type
Dynamic: home-page
Dynamic: license-file
Dynamic: requires-dist
Dynamic: requires-python
Dynamic: summary
